{"sampleFiles":[{"hasRelativeAssetsUrls":false,"path":"src/app/badge-sample-1/badge-sample-1.component.ts","content":"import { Component, OnInit } from \"@angular/core\";\nimport { Member } from \"../model/member.model\";\n\n@Component({\n  selector: \"app-badge-sample-1\",\n  styleUrls: [\"./badge-sample-1.component.css\"],\n  templateUrl: \"./badge-sample-1.component.html\"\n})\nexport class BadgeSample1Component implements OnInit {\n  public members: Member[] = [\n    new Member(\"Terrance Orta\", \"online\"),\n    new Member(\"Donna Price\", \"online\"),\n    new Member(\"Lisa Landers\", \"away\"),\n    new Member(\"Dorothy H. Spencer\", \"offline\")\n  ];\n\n  constructor() { }\n\n  public ngOnInit() {\n  }\n}\n"},{"hasRelativeAssetsUrls":false,"path":"src/app/badge-sample-1/badge-sample-1.component.html","content":"<igx-list>\n  <igx-list-item isHeader=\"true\">\n    Team Members (4)\n  </igx-list-item>\n  <igx-list-item *ngFor=\"let member of members\">\n    <div>\n      <div>\n        <span class=\"contact-name\">{{ member.name }}</span>\n        <span>({{ member.status }})</span>\n      </div>\n    </div>\n  </igx-list-item>\n</igx-list>"},{"hasRelativeAssetsUrls":false,"path":"src/app/badge-sample-1/badge-sample-1.component.css","content":".contact-name {\n  font-weight: 600; }\n"},{"hasRelativeAssetsUrls":false,"path":"src/app/model/member.model.ts","content":"export class Member {\n    public name: string;\n    public status: string;\n    public type: string;\n    public icon: string;\n\n    constructor(name: string, status: string) {\n        this.name = name;\n        this.status = status;\n        switch (status) {\n            case \"online\":\n                this.type = \"success\";\n                this.icon = \"check\";\n                break;\n            case \"away\":\n                this.type = \"warning\";\n                this.icon = \"schedule\";\n                break;\n            case \"offline\":\n                this.type = \"error\";\n                this.icon = \"remove\";\n                break;\n        }\n    }\n}\n"},{"hasRelativeAssetsUrls":false,"path":"src/app/app.module.ts","content":"import { NgModule } from \"@angular/core\";\nimport { FormsModule } from \"@angular/forms\";\nimport { BrowserModule } from \"@angular/platform-browser\";\nimport { BrowserAnimationsModule } from \"@angular/platform-browser/animations\";\nimport { AppComponent } from \"./app.component\";\r\nimport { \r\n\tIgxBadgeModule,\r\n\tIgxListModule\r\n } from \"igniteui-angular\";\r\nimport { BadgeSample1Component } from \"./badge-sample-1/badge-sample-1.component\";\n\n@NgModule({\n  bootstrap: [AppComponent],\n  declarations: [\n    AppComponent,\r\n\t\tBadgeSample1Component\n  ],\n  imports: [\n    BrowserModule,\n    BrowserAnimationsModule,\n    FormsModule,\r\n\t\tIgxBadgeModule,\r\n\t\tIgxListModule\n  ],\n  providers: [],\n  entryComponents: []\n})\nexport class AppModule {}\n"},{"hasRelativeAssetsUrls":false,"path":"src/app/app.component.html","content":"<app-badge-sample-1></app-badge-sample-1>"}],"sampleDependencies":"{\"@angular/animations\":\"7.1.1\",\"@angular/common\":\"7.1.1\",\"@angular/compiler\":\"7.1.1\",\"@angular/core\":\"7.1.1\",\"@angular/forms\":\"7.1.1\",\"@angular/http\":\"7.1.1\",\"@angular/platform-browser\":\"7.1.1\",\"@angular/platform-browser-dynamic\":\"7.1.1\",\"@angular/router\":\"7.1.1\",\"@types/hammerjs\":\"^2.0.35\",\"classlist.js\":\"^1.1.20150312\",\"core-js\":\"^2.4.1\",\"hammerjs\":\"^2.0.8\",\"igniteui-angular\":\"7.1.0\",\"immediate\":\"^3.2.3\",\"intl\":\"^1.2.5\",\"jszip\":\"^3.1.5\",\"rxjs\":\"^6.3.3\",\"tslib\":\"^1.9.0\",\"web-animations-js\":\"^2.3.1\",\"zone.js\":\"^0.8.26\"}"}